survivorpy/__init__.py
survivorpy/config.py
survivorpy/data.py
survivorpy/sync.py
survivorpy-0.1.2.dist-info/licenses/LICENSE
survivorpy-0.1.2.dist-info/METADATA
survivorpy-0.1.2.dist-info/WHEEL
survivorpy-0.1.2.dist-info/top_level.txt
survivorpy-0.1.2.dist-info/RECORD
