Metadata-Version: 2.4
Name: survivorpy
Version: 0.1.2
Summary: A Python wrapper for data from the R package survivoR.
Author: Jonny Comes
License: MIT
Project-URL: Homepage, https://github.com/jonnycomes/survivorpy
Project-URL: Repository, https://github.com/jonnycomes/survivorpy
Project-URL: Issues, https://github.com/jonnycomes/survivorpy/issues
Requires-Python: >=3.8
License-File: LICENSE
Requires-Dist: pandas>=2.0
Requires-Dist: requests>=2.31
Requires-Dist: appdirs>=1.4
Requires-Dist: pyarrow>=9.0.0
Dynamic: license-file
